
[
    {
        "in_reply_to_user_id":null,
        "text":"The app where you can listen to music is called \"iTunes\" on your Mac, \"iPod\" on your iPhone, and \"Music\" on your iPod -- confusing!",
        "favorited":false,
        "created_at":"Wed Dec 22 00:29:04 +0000 2010",
        "in_reply_to_status_id_str":null,
        "contributors":null,
        "geo":null,
        "in_reply_to_screen_name":null,
        "in_reply_to_user_id_str":null,
        "place":null,
        "in_reply_to_status_id":null,
        "source":"web",
        "retweeted":false,
        "retweet_count":6,
        "id_str":"17376037931319296",
        "coordinates":null,
        "user":
        {
            "profile_text_color":"333333",
            "followers_count":873,
            "is_translator":false,
            "listed_count":79,
            "lang":"en",
            "verified":false,
            "created_at":"Fri Aug 10 00:05:04 +0000 2007",
            "friends_count":56,
            "profile_sidebar_fill_color":"E6F6F9",
            "description":"Engineer, designer & philosopher interested in technology and human flourishing.",
            "profile_background_tile":true,
            "time_zone":"Central Time (US & Canada)",
            "url":"http:\/\/davidsiegel.org",
            "show_all_inline_media":false,
            "geo_enabled":false,
            "following":null,"notifications":null,"profile_link_color":"CC3366","location":"Minneapolis","contributors_enabled":false,"profile_sidebar_border_color":"DBE9ED","id_str":"8092322","profile_use_background_image":true,"protected":false,"follow_request_sent":null,
            "statuses_count":1590,"profile_background_color":"DBE9ED","profile_image_url":"http:\/\/a0.twimg.com\/profile_images\/1115347333\/45090_1400443052747_1282410081_31039256_7564995_n_normal.jpg",
            "name":"David Siegel",
            "profile_background_image_url":"http:\/\/a3.twimg.com\/profile_background_images\/143149214\/Screen_shot_2010-09-01_at_4.12.29_PM.png",
            "id":8092322,"utc_offset":-21600,"favourites_count":38,
            "screen_name":"davidsiegel"
        },
        "id":17376037931319296,
        "truncated":false}]